.coveragerc
.gitignore
.travis.yml
CHANGES.rst
CONTRIBUTORS.rst
MANIFEST.in
README.rst
bootstrap.py
buildout.cfg
setup.cfg
setup.py
docs/LICENSE.GPL
docs/LICENSE.txt
src/collective/__init__.py
src/collective.js.cycle2.egg-info/PKG-INFO
src/collective.js.cycle2.egg-info/SOURCES.txt
src/collective.js.cycle2.egg-info/dependency_links.txt
src/collective.js.cycle2.egg-info/entry_points.txt
src/collective.js.cycle2.egg-info/namespace_packages.txt
src/collective.js.cycle2.egg-info/not-zip-safe
src/collective.js.cycle2.egg-info/requires.txt
src/collective.js.cycle2.egg-info/top_level.txt
src/collective/js/__init__.py
src/collective/js/cycle2/__init__.py
src/collective/js/cycle2/configure.zcml
src/collective/js/cycle2/interfaces.py
src/collective/js/cycle2/testing.py
src/collective/js/cycle2/profiles/default/metadata.xml
src/collective/js/cycle2/resources/jquery.cycle2.caption2.js
src/collective/js/cycle2/resources/jquery.cycle2.caption2.min.js
src/collective/js/cycle2/resources/jquery.cycle2.carousel.js
src/collective/js/cycle2/resources/jquery.cycle2.carousel.min.js
src/collective/js/cycle2/resources/jquery.cycle2.center.js
src/collective/js/cycle2/resources/jquery.cycle2.center.min.js
src/collective/js/cycle2/resources/jquery.cycle2.flip.js
src/collective/js/cycle2/resources/jquery.cycle2.flip.min.js
src/collective/js/cycle2/resources/jquery.cycle2.ie-fade.js
src/collective/js/cycle2/resources/jquery.cycle2.ie-fade.min.js
src/collective/js/cycle2/resources/jquery.cycle2.js
src/collective/js/cycle2/resources/jquery.cycle2.min.js
src/collective/js/cycle2/resources/jquery.cycle2.scrollVert.js
src/collective/js/cycle2/resources/jquery.cycle2.scrollVert.min.js
src/collective/js/cycle2/resources/jquery.cycle2.shuffle.js
src/collective/js/cycle2/resources/jquery.cycle2.shuffle.min.js
src/collective/js/cycle2/resources/jquery.cycle2.swipe.js
src/collective/js/cycle2/resources/jquery.cycle2.swipe.min.js
src/collective/js/cycle2/resources/jquery.cycle2.tile.js
src/collective/js/cycle2/resources/jquery.cycle2.tile.min.js
src/collective/js/cycle2/resources/jquery.cycle2.video.js
src/collective/js/cycle2/resources/jquery.cycle2.video.min.js
src/collective/js/cycle2/tests/__init__.py
src/collective/js/cycle2/tests/test_setup.py
src/collective/js/cycle2/tests/test_upgrades.py
src/collective/js/cycle2/upgrades/__init__.py
src/collective/js/cycle2/upgrades/configure.zcml
