Metadata-Version: 1.1
Name: collective.js.cycle2
Version: 1.0b1
Summary: Integration of Cycle2 jQuery plugin in Plone.
Home-page: https://github.com/collective/collective.js.cycle2
Author: Simples Consultoria
Author-email: produtos@simplesconsultoria.com.br
License: UNKNOWN
Keywords: plone jquery plugin cycle2 slideshow
Platform: UNKNOWN
Classifier: Development Status :: 4 - Beta
Classifier: Environment :: Web Environment
Classifier: Framework :: Plone
Classifier: Framework :: Plone :: 4.2
Classifier: Framework :: Plone :: 4.3
Classifier: Framework :: Plone :: 5.0
Classifier: Intended Audience :: Developers
Classifier: Intended Audience :: System Administrators
Classifier: License :: OSI Approved :: GNU General Public License v2 (GPLv2)
Classifier: Operating System :: OS Independent
Classifier: Programming Language :: JavaScript
Classifier: Programming Language :: Python
Classifier: Programming Language :: Python :: 2.7
Classifier: Topic :: Software Development :: Libraries :: Python Modules
